django_translation_flags/__init__.py
django_translation_flags/app_settings.py
django_translation_flags/apps.py
django_translation_flags/urls.py
django_translation_flags/static/css/django-translation-flags.css
django_translation_flags/static/css/django-translation-flags.min.css
django_translation_flags/static/icons/rect/af.svg
django_translation_flags/static/icons/rect/ar.svg
django_translation_flags/static/icons/rect/az.svg
django_translation_flags/static/icons/rect/de.svg
django_translation_flags/static/icons/rect/en-au.svg
django_translation_flags/static/icons/rect/en.svg
django_translation_flags/static/icons/rect/es-ar.svg
django_translation_flags/static/icons/rect/es-mx.svg
django_translation_flags/static/icons/rect/es.svg
django_translation_flags/static/icons/rect/fr.svg
django_translation_flags/static/icons/rect/hi.svg
django_translation_flags/static/icons/rect/hu.svg
django_translation_flags/static/icons/rect/id.svg
django_translation_flags/static/icons/rect/it.svg
django_translation_flags/static/icons/rect/ja.svg
django_translation_flags/static/icons/rect/ko.svg
django_translation_flags/static/icons/rect/nl.svg
django_translation_flags/static/icons/rect/pl.svg
django_translation_flags/static/icons/rect/pt-br.svg
django_translation_flags/static/icons/rect/pt.svg
django_translation_flags/static/icons/rect/ru.svg
django_translation_flags/static/icons/rect/sv.svg
django_translation_flags/static/icons/rect/tr.svg
django_translation_flags/static/icons/rect/uk.svg
django_translation_flags/static/icons/rect/zh-cn.svg
django_translation_flags/static/icons/rect/zh-hans.svg
django_translation_flags/static/icons/rect/zh-hant.svg
django_translation_flags/static/icons/square/af.svg
django_translation_flags/static/icons/square/ar.svg
django_translation_flags/static/icons/square/az.svg
django_translation_flags/static/icons/square/de.svg
django_translation_flags/static/icons/square/en-au.svg
django_translation_flags/static/icons/square/en.svg
django_translation_flags-1.0.6.dist-info/LICENSE.md
django_translation_flags-1.0.6.dist-info/METADATA
django_translation_flags-1.0.6.dist-info/WHEEL
django_translation_flags-1.0.6.dist-info/top_level.txt
django_translation_flags-1.0.6.dist-info/RECORD
